easy_task/__init__.py
easy_task/base_module/__init__.py
easy_task/base_module/base_result.py
easy_task/base_module/base_setting.py
easy_task/base_module/base_task.py
easy_task/base_module/base_utils.py
easy_task/task_module/__init__.py
easy_task/task_module/model_for_cls.py
easy_task/task_module/model_for_ner.py
easy_task/task_module/result_for_cls.py
easy_task/task_module/result_for_ner.py
easy_task/task_module/task_for_cls.py
easy_task/task_module/task_for_ner.py
easy_task-0.0.30.dist-info/LICENSE
easy_task-0.0.30.dist-info/METADATA
easy_task-0.0.30.dist-info/WHEEL
easy_task-0.0.30.dist-info/top_level.txt
easy_task-0.0.30.dist-info/RECORD
