Metadata-Version: 2.1
Name: easy-task
Version: 0.0.30
Summary: make you easy to build deeplearning task
Home-page: https://github.com/AI-confused/easy_task
Author: black_tears
Author-email: 21860437@zju.edu.cn
Project-URL: Bug Tracker, https://github.com/AI-confused/easy_task/issues
Classifier: Programming Language :: Python :: 3
Classifier: License :: OSI Approved :: MIT License
Classifier: Operating System :: OS Independent
Requires-Python: >=3.5
License-File: LICENSE
